[{"plate_no":"KCB615","driver_name":"ABDUL","company":"TROJAN","client":"ICRC","contact":"256785495623","purpuse":"Delivery","arrival":{"date":"2/4/2023","time":"10:36:37 PM","recievedBy":"Konson"},"offloadDate":null,"status":true,"depature":{"date":"2/4/2023","time":"11:20:04 PM","depaturedBy":"Konson"},"_id":"5FDUepAatOSGfISZ"},{"plate_no":"KCB852VB","driver_name":"MUHAMED ALI","company":"TANSAL","client":"UNICEFE","contact":"095215423","purpuse":"Delivery","arrival":{"date":"2/4/2023","time":"11:09:48 PM","recievedBy":"Konson"},"offloadDate":null,"status":true,"depature":{"date":"2/4/2023","time":"11:21:21 PM","depaturedBy":"Konson"},"_id":"OYOH3itzRdvLtVx0"},{"plate_no":"KBW666V","driver_name":"Hassen","company":"TASAL","client":"UNICEFE","contact":"095231254","purpuse":"Delivery","arrival":{"date":"2/4/2023","time":"10:38:23 PM","recievedBy":"Christine"},"offloadDate":null,"status":true,"depature":null,"_id":"ROMbGoEDCBGmrxTZ"},{"plate_no":"KBJ851ML","driver_name":"MUSA ALI","company":"BOLLORE","client":"UNICEFE","contact":"095215478","purpuse":"Delivery","arrival":{"date":"2/4/2023","time":"10:50:47 PM","recievedBy":"Christine"},"offloadDate":null,"status":true,"depature":null,"_id":"TldSZqBP9ConMGmA"},{"plate_no":"KCA512NL","driver_name":"YUSIF","company":"TANSAL","client":"UNICEFE","contact":"0925321458","purpuse":"Delivery","arrival":{"date":"2/4/2023","time":"10:31:14 PM","recievedBy":"Konson"},"offloadDate":null,"status":true,"depature":{"date":"2/4/2023","time":"10:33:48 PM","depaturedBy":"Konson"},"_id":"erc283pexk3777ey"},{"plate_no":"KCX96L","driver_name":"JAMAL IBRAHAM ","company":"TROJAN","client":"UNICEFE","contact":"0925321458","purpuse":"Delivery","arrival":{"date":"2/4/2023","time":"11:23:04 PM","recievedBy":"Konson"},"offloadDate":null,"status":false,"depature":null,"_id":"f9drr80gT3o7jTwu"},{"plate_no":"KCX103Q","driver_name":"IBRAHAM MANUAL","company":"TANSAL","client":"UNICEFE","contact":"256785412549","purpuse":"Delivery","arrival":{"date":"2/4/2023","time":"10:19:25 PM","recievedBy":"Konson"},"offloadDate":null,"status":true,"depature":{"date":"2/4/2023","time":"10:27:04 PM","depaturedBy":"Konson"},"_id":"k2B0rVfolkx9jFfv"}]